CHANGES.rst
MANIFEST.in
README.rst
setup.py
js/__init__.py
js.bootstrap_select.egg-info/PKG-INFO
js.bootstrap_select.egg-info/SOURCES.txt
js.bootstrap_select.egg-info/dependency_links.txt
js.bootstrap_select.egg-info/entry_points.txt
js.bootstrap_select.egg-info/namespace_packages.txt
js.bootstrap_select.egg-info/not-zip-safe
js.bootstrap_select.egg-info/requires.txt
js.bootstrap_select.egg-info/top_level.txt
js/bootstrap_select/__init__.py
js/bootstrap_select/test_bootstrap_select.txt
js/bootstrap_select/resources/bootstrap-select.css
js/bootstrap_select/resources/bootstrap-select.js
js/bootstrap_select/resources/bootstrap-select.min.css
js/bootstrap_select/resources/bootstrap-select.min.js