Metadata-Version: 1.1
Name: js.bootstrap-select
Version: 1.5.2
Summary: Fanstatic packaging of bootstrap-select.js.
Home-page: https://github.com/tmassman/js.bootstrap_select
Author: Thomas Massmann
Author-email: thomas.massmann@it-spir.it
License: BSD
Download-URL: http://pypi.python.org/pypi/js.bootstrap_select
Platform: UNKNOWN
